ShijieshangZuishenqide24tangke/Dockerfile
ShijieshangZuishenqide24tangke/README.md
ShijieshangZuishenqide24tangke/__init__.py
ShijieshangZuishenqide24tangke/__main__.py
ShijieshangZuishenqide24tangke/file.epub
ShijieshangZuishenqide24tangke/index.html
ShijieshangZuishenqide24tangke/css/__init__.py
ShijieshangZuishenqide24tangke/css/annotations.css
ShijieshangZuishenqide24tangke/css/main.css
ShijieshangZuishenqide24tangke/css/normalize.css
ShijieshangZuishenqide24tangke/css/popup.css
ShijieshangZuishenqide24tangke/font/__init__.py
ShijieshangZuishenqide24tangke/font/fontello.eot
ShijieshangZuishenqide24tangke/font/fontello.svg
ShijieshangZuishenqide24tangke/font/fontello.ttf
ShijieshangZuishenqide24tangke/font/fontello.woff
ShijieshangZuishenqide24tangke/img/__init__.py
ShijieshangZuishenqide24tangke/img/annotator-glyph-sprite.png
ShijieshangZuishenqide24tangke/img/annotator-icon-sprite.png
ShijieshangZuishenqide24tangke/img/apple-touch-icon.png
ShijieshangZuishenqide24tangke/img/cancelfullscreen.png
ShijieshangZuishenqide24tangke/img/close.png
ShijieshangZuishenqide24tangke/img/fullscreen.png
ShijieshangZuishenqide24tangke/img/loader.gif
ShijieshangZuishenqide24tangke/img/menu-icon.png
ShijieshangZuishenqide24tangke/img/save.png
ShijieshangZuishenqide24tangke/img/saved.png
ShijieshangZuishenqide24tangke/img/settings-s.png
ShijieshangZuishenqide24tangke/img/settings.png
ShijieshangZuishenqide24tangke/img/star.png
ShijieshangZuishenqide24tangke/js/__init__.py
ShijieshangZuishenqide24tangke/js/epub.js
ShijieshangZuishenqide24tangke/js/epub.min.js
ShijieshangZuishenqide24tangke/js/epub.min.map
ShijieshangZuishenqide24tangke/js/hooks.min.js
ShijieshangZuishenqide24tangke/js/hooks.min.map
ShijieshangZuishenqide24tangke/js/reader.js
ShijieshangZuishenqide24tangke/js/reader.js.map
ShijieshangZuishenqide24tangke/js/reader.min.js
ShijieshangZuishenqide24tangke/js/reader.min.map
ShijieshangZuishenqide24tangke/js/hooks/__init__.py
shijieshang_zuishenqide_24tangke-2022.10.7.1.dist-info/METADATA
shijieshang_zuishenqide_24tangke-2022.10.7.1.dist-info/WHEEL
shijieshang_zuishenqide_24tangke-2022.10.7.1.dist-info/entry_points.txt
shijieshang_zuishenqide_24tangke-2022.10.7.1.dist-info/top_level.txt
shijieshang_zuishenqide_24tangke-2022.10.7.1.dist-info/RECORD
